dappleyPython/DError.py
dappleyPython/Dappley.py
dappleyPython/__init__.py
dappleyPython/chain/TransactionManager.py
dappleyPython/chain/UtxoManager.py
dappleyPython/chain/__init__.py
dappleyPython/lib/__init__.py
dappleyPython/lib/protobuf/__init__.py
dappleyPython/lib/protobuf/block_pb2.py
dappleyPython/lib/protobuf/block_pb2_grpc.py
dappleyPython/lib/protobuf/datastore_pb2.py
dappleyPython/lib/protobuf/datastore_pb2_grpc.py
dappleyPython/lib/protobuf/peer_pb2.py
dappleyPython/lib/protobuf/peer_pb2_grpc.py
dappleyPython/lib/protobuf/rpc_pb2.py
dappleyPython/lib/protobuf/rpc_pb2_grpc.py
dappleyPython/lib/protobuf/transactionBase_pb2.py
dappleyPython/lib/protobuf/transactionBase_pb2_grpc.py
dappleyPython/lib/protobuf/transaction_pb2.py
dappleyPython/lib/protobuf/transaction_pb2_grpc.py
dappleyPython/lib/protobuf/utxo_pb2.py
dappleyPython/lib/protobuf/utxo_pb2_grpc.py
dappleyPython/model/Transaction.py
dappleyPython/model/TxInput.py
dappleyPython/model/TxOutput.py
dappleyPython/model/Utxo.py
dappleyPython/model/__init__.py
dappleyPython/rpcnet/RPCClient.py
dappleyPython/rpcnet/__init__.py
dappleyPython/rpcnet/rpct_test.py
dappleyPython/util/AddressUtil.py
dappleyPython/util/Constant.py
dappleyPython/util/ConvertUtil.py
dappleyPython/util/HashUtil.py
dappleyPython/util/__init__.py
dappleyPython-0.0.1.dist-info/DESCRIPTION.rst
dappleyPython-0.0.1.dist-info/METADATA
dappleyPython-0.0.1.dist-info/RECORD
dappleyPython-0.0.1.dist-info/WHEEL
dappleyPython-0.0.1.dist-info/metadata.json
dappleyPython-0.0.1.dist-info/top_level.txt
